rthor/__init__.py
rthor/_core.py
rthor/_input.py
rthor/_permutations.py
rthor/_utils.py
rthor/_validation.py
rthor/_vectorized.py
rthor/_version.py
rthor/formatting.py
rthor/rthor.py
rthor-0.2.1.dist-info/licenses/LICENSE.md
rthor-0.2.1.dist-info/METADATA
rthor-0.2.1.dist-info/WHEEL
rthor-0.2.1.dist-info/top_level.txt
rthor-0.2.1.dist-info/RECORD
