Metadata-Version: 2.4
Name: rthor
Version: 0.2.1
Summary: Python implementation of RTHOR (Randomization test of hypothesized order relations)
Author-email: Andrew Mitchell <andrew.mitchell.research@gmail.com>
License-Expression: MIT
Project-URL: documentation, https://drandrewmitchell.com/rthor
Project-URL: homepage, https://drandrewmitchell.com/rthor
Project-URL: repository, https://github.com/MitchellAcoustics/rthor
Classifier: Operating System :: POSIX
Classifier: Programming Language :: Python :: 3
Classifier: Programming Language :: Python :: 3 :: Only
Classifier: Programming Language :: Python :: 3.11
Classifier: Programming Language :: Python :: 3.12
Classifier: Programming Language :: Python :: 3.13
Classifier: Typing :: Typed
Requires-Python: >=3.11
License-File: LICENSE.md
Requires-Dist: numpy>=1.24.0
Requires-Dist: pandas>=2.0.0
Provides-Extra: all
Requires-Dist: rthor[rich]; extra == "all"
Provides-Extra: rich
Requires-Dist: rich>=14.1.0; extra == "rich"
Dynamic: license-file
